tkdev4/__init__.py
tkdev4/__main__.py
tkdev4/example-2.py
tkdev4/example-3.py
tkdev4/example.py
tkdev4/devcore/__init__.py
tkdev4/devdraw/__init__.py
tkdev4/devicon/__init__.py
tkdev4/devplyer/__init__.py
tkdev4/devpre/__init__.py
tkdev4/devtcl/__init__.py
tkdev4-4.2.7.dist-info/METADATA
tkdev4-4.2.7.dist-info/WHEEL
tkdev4-4.2.7.dist-info/top_level.txt
tkdev4-4.2.7.dist-info/RECORD
