Metadata-Version: 2.1
Name: tkdev4
Version: 4.2.7
Summary: tkinterDev超级工具库，仅为Windows开发支持。
Home-page: https://xiangqinxidevelopment.jetbrains.space/p/tkinterdev
Author: XiangQinxi
Author-email: XiangQinxi@outlook.com
Classifier: Programming Language :: Python :: 3
Classifier: License :: OSI Approved :: MIT License
Classifier: Operating System :: OS Independent
Requires-Python: >=3.6
Requires-Dist: tqdm
Requires-Dist: colorama
Requires-Dist: windnd
